napari_skimage_regionprops/__init__.py
napari_skimage_regionprops/_all_frames.py
napari_skimage_regionprops/_load_csv.py
napari_skimage_regionprops/_measure_points.py
napari_skimage_regionprops/_multichannel.py
napari_skimage_regionprops/_parametric_images.py
napari_skimage_regionprops/_process_tables.py
napari_skimage_regionprops/_regionprops.py
napari_skimage_regionprops/_table.py
napari_skimage_regionprops/_utilities.py
napari_skimage_regionprops/_tests/__init__.py
napari_skimage_regionprops/_tests/test_function.py
napari_skimage_regionprops/_tests/test_multichannel.py
napari_skimage_regionprops/_tests/test_timelapse.py
napari_skimage_regionprops-0.10.1.dist-info/LICENSE
napari_skimage_regionprops-0.10.1.dist-info/METADATA
napari_skimage_regionprops-0.10.1.dist-info/WHEEL
napari_skimage_regionprops-0.10.1.dist-info/entry_points.txt
napari_skimage_regionprops-0.10.1.dist-info/top_level.txt
napari_skimage_regionprops-0.10.1.dist-info/RECORD
