Metadata-Version: 2.1
Name: napari-skimage-regionprops
Version: 0.10.1
Summary: A regionprops table widget plugin for napari
Home-page: https://github.com/haesleinhuepf/napari-skimage-regionprops
Author: Marcelo Zoccoler, Robert Haase
Author-email: robert.haase@tu-dresden.de
License: BSD-3
Classifier: Development Status :: 4 - Beta
Classifier: Intended Audience :: Science/Research
Classifier: Framework :: napari
Classifier: Topic :: Scientific/Engineering :: Image Processing
Classifier: Topic :: Scientific/Engineering :: Information Analysis
Classifier: Programming Language :: Python
Classifier: Programming Language :: Python :: 3
Classifier: Programming Language :: Python :: 3.8
Classifier: Programming Language :: Python :: 3.9
Classifier: Programming Language :: Python :: 3.10
Classifier: Operating System :: OS Independent
Classifier: License :: OSI Approved :: BSD License
Requires-Python: >=3.8
License-File: LICENSE
Requires-Dist: napari-plugin-engine (>=0.1.4)
Requires-Dist: numpy
Requires-Dist: scikit-image
Requires-Dist: napari
Requires-Dist: pandas
Requires-Dist: napari-tools-menu (>=0.1.19)
Requires-Dist: napari-workflows
Requires-Dist: imageio (!=2.22.1)
Requires-Dist: Deprecated
